jstprove_test-0.1.0.data/data/Cargo.lock
jstprove_test-0.1.0.data/data/Cargo.toml
jstprove_test-0.1.0.data/data/README.md
jstprove_test-0.1.0.data/data/input.json
jstprove_test-0.1.0.data/data/rust-toolchain.toml
jstprove_test-0.1.0.data/data/jstprove_data/rust/Cargo.toml
jstprove_test-0.1.0.data/data/jstprove_data/rust/build_layers.rs
jstprove_test-0.1.0.data/data/jstprove_data/rust/constant.rs
jstprove_test-0.1.0.data/data/jstprove_data/rust/constants.rs
jstprove_test-0.1.0.data/data/jstprove_data/rust/conv.rs
jstprove_test-0.1.0.data/data/jstprove_data/rust/core_math.rs
jstprove_test-0.1.0.data/data/jstprove_data/rust/flatten.rs
jstprove_test-0.1.0.data/data/jstprove_data/rust/gemm.rs
jstprove_test-0.1.0.data/data/jstprove_data/rust/generic_demo.rs
jstprove_test-0.1.0.data/data/jstprove_data/rust/graph_pattern_matching.rs
jstprove_test-0.1.0.data/data/jstprove_data/rust/io_reader.rs
jstprove_test-0.1.0.data/data/jstprove_data/rust/json_array.rs
jstprove_test-0.1.0.data/data/jstprove_data/rust/layer_ops.rs
jstprove_test-0.1.0.data/data/jstprove_data/rust/lib.rs
jstprove_test-0.1.0.data/data/jstprove_data/rust/main_runner.rs
jstprove_test-0.1.0.data/data/jstprove_data/rust/maxpool.rs
jstprove_test-0.1.0.data/data/jstprove_data/rust/mod.rs
jstprove_test-0.1.0.data/data/jstprove_data/rust/onnx_model.rs
jstprove_test-0.1.0.data/data/jstprove_data/rust/onnx_types.rs
jstprove_test-0.1.0.data/data/jstprove_data/rust/quantization.rs
jstprove_test-0.1.0.data/data/jstprove_data/rust/relu.rs
jstprove_test-0.1.0.data/data/jstprove_data/rust/reshape.rs
jstprove_test-0.1.0.data/data/jstprove_data/rust/shaping.rs
jstprove_test-0.1.0.data/data/jstprove_data/rust/simple_circuit.rs
jstprove_test-0.1.0.data/data/jstprove_data/rust/tensor_ops.rs
python/__init__.py
python/_version.py
python/core/__init__.py
python/core/circuit_models/__init__.py
python/core/circuit_models/generic_onnx.py
python/core/circuit_models/simple_circuit.py
python/core/circuits/__init__.py
jstprove_test-0.1.0.dist-info/METADATA
jstprove_test-0.1.0.dist-info/WHEEL
jstprove_test-0.1.0.dist-info/entry_points.txt
jstprove_test-0.1.0.dist-info/top_level.txt
jstprove_test-0.1.0.dist-info/RECORD
