Metadata-Version: 2.4
Name: jstprove-test
Version: 0.1.0
Summary: JSTProve — Verifiable ML by Inference Labs (Python CLI)
Author: Inference Labs
Keywords: zkml,ml,onnx,proofs,gkr
Requires-Python: >=3.10
Requires-Dist: numpy==2.2.6
Requires-Dist: onnx==1.17.0
Requires-Dist: onnxruntime==1.21.0
Requires-Dist: onnxruntime-extensions==0.14.0
Requires-Dist: psutil==7.0.0
Requires-Dist: requests==2.32.3
Requires-Dist: scikit-learn==1.6.1
Requires-Dist: toml==0.10.2
Requires-Dist: torch==2.6.0
Requires-Dist: transformers==4.52.4
Provides-Extra: dev
Requires-Dist: pytest==8.3.5; extra == "dev"
Requires-Dist: pytest-html==4.1.1; extra == "dev"
Requires-Dist: pre-commit; extra == "dev"
